af3cli/__init__.py
af3cli/__main__.py
af3cli/bond.py
af3cli/builder.py
af3cli/exception.py
af3cli/input.py
af3cli/io.py
af3cli/ligand.py
af3cli/mixin.py
af3cli/seqid.py
af3cli/sequence.py
af3cli-0.4.2.dist-info/METADATA
af3cli-0.4.2.dist-info/WHEEL
af3cli-0.4.2.dist-info/entry_points.txt
af3cli-0.4.2.dist-info/licenses/LICENSE
af3cli-0.4.2.dist-info/RECORD
