Metadata-Version: 2.4
Name: af3cli
Version: 0.4.2
Summary: A command-line interface and Python library for generating AlphaFold3 input files.
Project-URL: Repository, https://github.com/SLx64/af3cli.git
Author-email: Lukas Schulig <schuligl@uni-greifswald.de>, Philipp Döpner <doepnerp@uni-greifswald.de>, Mark Dörr <mark.doerr@uni-greifswald.de>
License-Expression: MIT
License-File: LICENSE
Keywords: AlphaFold,CLI
Classifier: Development Status :: 4 - Beta
Classifier: Intended Audience :: Science/Research
Classifier: License :: OSI Approved :: MIT License
Classifier: Programming Language :: Python :: 3
Classifier: Topic :: Scientific/Engineering :: Bio-Informatics
Requires-Python: >=3.11
Requires-Dist: fire>=0.7.0
